README.rst
setup.py
pyx/__init__.py
pyx/cmd.py
pyx/http.py
pyx/io.py
pyx/log.py
pyx/version.py
pyx/tests/__init__.py
pyx/tests/test_http.py
pyx/tests/test_io.py
pyxserver.egg-info/PKG-INFO
pyxserver.egg-info/SOURCES.txt
pyxserver.egg-info/dependency_links.txt
pyxserver.egg-info/entry_points.txt
pyxserver.egg-info/not-zip-safe
pyxserver.egg-info/requires.txt
pyxserver.egg-info/top_level.txt