Metadata-Version: 1.1
Name: pyxserver
Version: 0.1.4
Summary: Yet another async web server
Home-page: https://github.com/l04m33/pyx
Author: Kay Zheng
Author-email: l04m33@gmail.com
License: http://l04m33.mit-license.org/
Keywords: http,web,server
Platform: UNKNOWN
Classifier: License :: OSI Approved :: MIT License
Classifier: Programming Language :: Python :: 3.4
